ecu/__init__.py
ecu/utils.py
ecu/modules/confirm.py
ecu/modules/frame.py
ecu/modules/select.py
ecu/modules/spinner.py
ecu-0.5.dist-info/licenses/LICENSE
ecu-0.5.dist-info/METADATA
ecu-0.5.dist-info/WHEEL
ecu-0.5.dist-info/top_level.txt
ecu-0.5.dist-info/RECORD
