Metadata-Version: 2.4
Name: ecu
Version: 0.5
Summary: Yet another CLI helper lib
Author-email: Egsagon <egsagon12@gmail.com>
License: MIT License
Project-URL: Repository, https://github.com/Egsagon/ECU
Keywords: cli,util,terminal
Classifier: Development Status :: 5 - Production/Stable
Classifier: Programming Language :: Python
Requires-Python: >=3.9
License-File: LICENSE
Requires-Dist: readchar
Dynamic: license-file
